<?xml version="1.0" encoding="UTF-8" standalone="yes"?>
<XmlHardware>
    <devices>
        <XmlPlatinumTwitter>
            <name>RightJ5Motor</name>
            <alias>1</alias>
            <address>1</address>
            <actuatorPackage>J5R_Nadia</actuatorPackage>
            <reversePositiveMotorDirection>false</reversePositiveMotorDirection>
            <inputOffset>0</inputOffset>
            <outputOffset>0</outputOffset>
            <present>false</present>
        </XmlPlatinumTwitter>
        <XmlPlatinumTwitter>
            <name>RightJ6Motor</name>
            <alias>1</alias>
            <address>1</address>
            <actuatorPackage>J6R_Nadia</actuatorPackage>
            <reversePositiveMotorDirection>false</reversePositiveMotorDirection>
            <inputOffset>0</inputOffset>
            <outputOffset>0</outputOffset>
            <present>false</present>
        </XmlPlatinumTwitter>
        <XmlPlatinumTwitter>
            <name>RightJ7Motor</name>
            <alias>1</alias>
            <address>1</address>
            <actuatorPackage>J7R_Nadia</actuatorPackage>
            <reversePositiveMotorDirection>false</reversePositiveMotorDirection>
            <inputOffset>0</inputOffset>
            <outputOffset>0</outputOffset>
            <present>false</present>
        </XmlPlatinumTwitter>

        <XmlEtherSnacksBoard>
            <name>RightForearmEtherSnacksBoard</name>
            <alias>1</alias>
            <address>2</address>
            <present>false</present>
            <XmlIMU>
                <name>RightForearmIMU</name>
                <alias>0</alias>
                <address>1</address>
                <imuType>TDK</imuType>
                <present>true</present>
            </XmlIMU>
            <XmlTemperatureSensor>
                <name>RightForearmTempSensor</name>
                <conversionConstant>1.0</conversionConstant>
            </XmlTemperatureSensor>
        </XmlEtherSnacksBoard>
    </devices>
    <transmissions>
        <XmlCycloidMechanism>
            <jointName>RIGHT_WRIST_Z</jointName>
            <motorName>RightJ5Motor</motorName>
            <jointPositionOffset>0.0</jointPositionOffset>
            <lowerJointLimit>-2.61799</lowerJointLimit>
            <upperJointLimit>2.61799</upperJointLimit>
            <torqueBreakFrequency>100.0</torqueBreakFrequency>
            <present>false</present>
        </XmlCycloidMechanism>
        <XmlCycloidMechanism>
            <jointName>RIGHT_WRIST_X</jointName>
            <motorName>RightJ6Motor</motorName>
            <jointPositionOffset>0.0</jointPositionOffset>
            <lowerJointLimit>-0.610865</lowerJointLimit>
            <upperJointLimit>1.8326</upperJointLimit>
            <torqueBreakFrequency>100.0</torqueBreakFrequency>
            <present>false</present>
        </XmlCycloidMechanism>
        <XmlCycloidMechanism>
            <jointName>RIGHT_GRIPPER_Z</jointName>
            <motorName>RightJ7Motor</motorName>
            <jointPositionOffset>0.0</jointPositionOffset>
            <lowerJointLimit>-2.61799</lowerJointLimit>
            <upperJointLimit>2.61799</upperJointLimit>
            <torqueBreakFrequency>100.0</torqueBreakFrequency>
            <present>false</present>
        </XmlCycloidMechanism>
    </transmissions>
</XmlHardware>